kkwebapi/EmocreWebAPI.py
kkwebapi/KoikatuSunshineWebAPI.py
kkwebapi/KoikatuWebAPI.py
kkwebapi/__init__.py
kkwebapi-0.1.3.dist-info/WHEEL
kkwebapi-0.1.3.dist-info/METADATA
kkwebapi-0.1.3.dist-info/RECORD
