Metadata-Version: 2.1
Name: kkwebapi
Version: 0.1.3
Summary: Web API wrapper for Koikatu / EmotionCreators official uploader.
Home-page: https://github.com/great-majority/KoikatuWebAPI
Author: great-majority
Author-email: yosaku.ideal+github@gmail.com
Requires-Python: >=3.7.1,<4.0.0
Classifier: Programming Language :: Python :: 3
Classifier: Programming Language :: Python :: 3.10
Classifier: Programming Language :: Python :: 3.8
Classifier: Programming Language :: Python :: 3.9
Requires-Dist: pandas (>=1.3.0,<2.0.0)
Requires-Dist: requests (>=2.26.0,<3.0.0)
